techspecs/__init__.py
techspecs/techspecs.py
techspecs-1.0.8.dist-info/LICENSE
techspecs-1.0.8.dist-info/METADATA
techspecs-1.0.8.dist-info/WHEEL
techspecs-1.0.8.dist-info/top_level.txt
techspecs-1.0.8.dist-info/RECORD
