Metadata-Version: 2.1
Name: techspecs
Version: 1.0.8
Summary: TechSpecs library for python
Home-page: https://github.com/techspecs/techspecs-python
Author: TechSpecs
Author-email: support@techspecs.io
Project-URL: Bug Tracker, https://github.com/techspecs/techspecs-python/issues
Keywords: TechSpecs API,specifications,phone specs,tablet specs,laptop specs,specs,smartwatch specs,smartphone specs,smartphones,tablets,smartwatches,laptops,Smartphone Specifications,Tablet Specifications,Smartwatch Specifications,Laptop Specifications,Technical Specifications,consumer electronics,ecommerce,techspecs-python,techspecs python,specifications library,tech specs API,tech specs
Classifier: Programming Language :: Python :: 3
Classifier: License :: OSI Approved :: MIT License
Classifier: Operating System :: OS Independent
Requires-Python: >=3.6
License-File: LICENSE
